{
  "episode_id": "EP02",
  "episode_number": 2,
  "episode_label": "第2集",
  "title": "四年前那个夜晚（上）",
  "goal": "沈念歌被设计灌醉送入陆景琛房间，醒来后被管家甩支票赶走——而她不知道的是，陆景琛当晚也被下了药，同样不记得发生了什么。两个被操控的人，以为自己是\"自愿的\"。真正的幕后黑手，究竟是谁？",
  "conflict": "陆景琛在医院偶遇沈念歌母子，萌宝一句\"你是爸爸吗\"震动了他。他下令调查，安排DNA检测。",
  "emotions": [
    "闪回",
    "慈善晚宴",
    "陷阱"
  ],
  "hook": "沈念歌被设计灌醉送入陆景琛房间，醒来后被管家甩支票赶走——而她不知道的是，陆景琛当晚也被下了药，同样不记得发生了什么。两个被操控的人，以为自己是\"自愿的\"。真正的幕后黑手，究竟是谁？",
  "source_basis": [
    "/Users/leiyang/Desktop/Coding/Short_videoGEN/screen_script/归档/ep002.md"
  ],
  "story_function": "screen_script_source_episode"
}
